LICENSE
MANIFEST.in
README
setup.py
qubell/__init__.py
qubell/api/__init__.py
qubell/api/__main__.py
qubell/api/globals.py
qubell/api/private/__init__.py
qubell/api/private/application.py
qubell/api/private/common.py
qubell/api/private/environment.py
qubell/api/private/exceptions.py
qubell/api/private/instance.py
qubell/api/private/manifest.py
qubell/api/private/organization.py
qubell/api/private/platform.py
qubell/api/private/revision.py
qubell/api/private/role.py
qubell/api/private/service.py
qubell/api/private/user.py
qubell/api/private/zone.py
qubell/api/private/testing/__init__.py
qubell/api/private/testing/sandbox_testcase.py
qubell/api/private/testing/setup_once.py
qubell/api/provider/__init__.py
qubell/api/provider/jwtauth.py
qubell/api/provider/router.py
qubell/api/testing/__init__.py
qubell/api/tools/__init__.py
qubell/cli/__init__.py
qubell/cli/__main__.py
qubell/cli/yamlutils.py
qubell/monitor/__init__.py
qubell/monitor/monitor.py
qubell/monitor/monitor_manifests/monitor.yml
qubell/monitor/monitor_manifests/monitor_child.yml
qubell/tests/__init__.py
qubell/tests/common/__init__.py
qubell/tests/common/test_activitylog.py
qubell/tests/common/test_entity_list.py
qubell/tests/common/test_retry.py
qubell/tests/provider/__init__.py
qubell/tests/provider/test_route_decorators.py
qubell/tests/provider/test_router.py
qubell/tests/testing/__init__.py
qubell/tests/testing/test_environment_decorator.py
qubell/tests/testing/test_norm.py
qubell/tests/testing/test_values_decorator.py
qubell_api_python_client.egg-info/PKG-INFO
qubell_api_python_client.egg-info/SOURCES.txt
qubell_api_python_client.egg-info/dependency_links.txt
qubell_api_python_client.egg-info/entry_points.txt
qubell_api_python_client.egg-info/requires.txt
qubell_api_python_client.egg-info/top_level.txt