Metadata-Version: 1.0
Name: qubell-api-python-client
Version: 1.66.47.43
Summary: Qubell platform client library
Home-page: https://github.com/qubell/contrib-python-qubell-client
Author: Vasyl Khomenko
Author-email: vkhomenko@qubell.com
License: Apache License
